MANIFEST.in
README.rst
distribute_setup.py
setup.py
janrain/__init__.py
janrain/django/__init__.py
janrain/django/backends.py
janrain/django/capture.py
janrain/django/decorators.py
janrain/django/middleware.py
janrain/django/models.py
janrain/django/session.py
janrain/django/signals.py
janrain/django/urls.py
janrain/django/views.py
janrain_django.egg-info/PKG-INFO
janrain_django.egg-info/SOURCES.txt
janrain_django.egg-info/dependency_links.txt
janrain_django.egg-info/namespace_packages.txt
janrain_django.egg-info/requires.txt
janrain_django.egg-info/top_level.txt