Metadata-Version: 1.1
Name: janrain-django
Version: 0.1.2
Summary: Janrain integration with Django
Home-page: http://developers.janrain.com/
Author: Micah Carrick
Author-email: micah@janrain.com
License: UNKNOWN
Platform: UNKNOWN
Classifier: Development Status :: 4 - Beta
Classifier: Environment :: Console
Classifier: Intended Audience :: Developers
Classifier: Operating System :: OS Independent
Classifier: Programming Language :: Python
Classifier: Topic :: Software Development :: Libraries :: Python Modules
Classifier: Topic :: Internet :: WWW/HTTP
Classifier: License :: OSI Approved :: MIT License
